pyexcel_openpyxlx/__init__.py
pyexcel_openpyxlx/app.py
pyexcel_openpyxlx-0.1.0.1.dist-info/WHEEL
pyexcel_openpyxlx-0.1.0.1.dist-info/METADATA
pyexcel_openpyxlx-0.1.0.1.dist-info/RECORD
